merilang/__init__.py
merilang/__main__.py
merilang/ast_nodes.py
merilang/ast_nodes_enhanced.py
merilang/builtins.py
merilang/cli.py
merilang/environment.py
merilang/errors.py
merilang/errors_enhanced.py
merilang/interpreter.py
merilang/interpreter_enhanced.py
merilang/lexer.py
merilang/lexer_enhanced.py
merilang/parser.py
merilang/parser_enhanced.py
merilang/py.typed
merilang-1.0.2.dist-info/licenses/LICENSE
merilang-1.0.2.dist-info/METADATA
merilang-1.0.2.dist-info/WHEEL
merilang-1.0.2.dist-info/entry_points.txt
merilang-1.0.2.dist-info/top_level.txt
merilang-1.0.2.dist-info/RECORD
