Metadata-Version: 2.4
Name: merilang
Version: 1.0.2
Summary: A desi toy programming language built with Python
Author: DesiLang Community
License: MIT
Project-URL: Homepage, https://github.com/XploitMonk0x01/merilang
Project-URL: Documentation, https://github.com/XploitMonk0x01/merilang#readme
Project-URL: Repository, https://github.com/XploitMonk0x01/merilang
Project-URL: Bug Tracker, https://github.com/XploitMonk0x01/merilang/issues
Keywords: programming-language,interpreter,desi,education,learning
Classifier: Development Status :: 4 - Beta
Classifier: Intended Audience :: Education
Classifier: Intended Audience :: Developers
Classifier: License :: OSI Approved :: MIT License
Classifier: Programming Language :: Python :: 3
Classifier: Programming Language :: Python :: 3.12
Classifier: Topic :: Education
Classifier: Topic :: Software Development :: Interpreters
Requires-Python: >=3.12
License-File: LICENSE
Requires-Dist: termcolor>=2.0.0
Provides-Extra: dev
Requires-Dist: pytest>=7.0.0; extra == "dev"
Requires-Dist: pytest-cov>=4.0.0; extra == "dev"
Provides-Extra: playground
Requires-Dist: flask>=3.0.0; extra == "playground"
Dynamic: license-file
